waldur_mcp_server/__init__.py
waldur_mcp_server/meta.yaml
waldur_mcp_server/server.py
waldur_mcp_server-0.1.1.dist-info/METADATA
waldur_mcp_server-0.1.1.dist-info/WHEEL
waldur_mcp_server-0.1.1.dist-info/entry_points.txt
waldur_mcp_server-0.1.1.dist-info/licenses/LICENSE.md
waldur_mcp_server-0.1.1.dist-info/RECORD
