Metadata-Version: 2.4
Name: waldur-mcp-server
Version: 0.1.1
Summary: Waldur MCP server project
License-File: LICENSE.md
Requires-Python: >=3.13
Requires-Dist: httpx>=0.28.1
Requires-Dist: mcp[cli]>=1.2.0
